nutrient_dws/__init__.py
nutrient_dws/client.py
nutrient_dws/errors.py
nutrient_dws/http.py
nutrient_dws/inputs.py
nutrient_dws/py.typed
nutrient_dws/workflow.py
nutrient_dws/builder/__init__.py
nutrient_dws/builder/base_builder.py
nutrient_dws/builder/builder.py
nutrient_dws/builder/constant.py
nutrient_dws/builder/staged_builders.py
nutrient_dws/types/__init__.py
nutrient_dws/types/account_info.py
nutrient_dws/types/analyze_response.py
nutrient_dws/types/build_actions.py
nutrient_dws/types/build_instruction.py
nutrient_dws/types/build_output.py
nutrient_dws/types/build_response_json.py
nutrient_dws/types/create_auth_token.py
nutrient_dws/types/error_response.py
nutrient_dws/types/file_handle.py
nutrient_dws/types/input_parts.py
nutrient_dws/types/misc.py
nutrient_dws/types/redact_data.py
nutrient_dws/types/sign_request.py
nutrient_dws/types/annotation/__init__.py
nutrient_dws/types/annotation/base.py
nutrient_dws/types/annotation/ellipse.py
nutrient_dws/types/annotation/image.py
nutrient_dws/types/annotation/ink.py
nutrient_dws/types/annotation/line.py
nutrient_dws/types/annotation/link.py
nutrient_dws/types/annotation/markup.py
nutrient_dws/types/annotation/note.py
nutrient_dws/types/annotation/polygon.py
nutrient_dws/types/annotation/polyline.py
nutrient_dws/types/annotation/rectangle.py
nutrient_dws/types/annotation/redaction.py
nutrient_dws/types/annotation/stamp.py
nutrient_dws/types/annotation/text.py
nutrient_dws/types/annotation/widget.py
nutrient_dws/types/instant_json/__init__.py
nutrient_dws/types/instant_json/actions.py
nutrient_dws/types/instant_json/attachments.py
nutrient_dws/types/instant_json/bookmark.py
nutrient_dws/types/instant_json/comment.py
nutrient_dws/types/instant_json/form_field.py
nutrient_dws/types/instant_json/form_field_value.py
nutrient_dws/utils/__init__.py
nutrient_dws/utils/version.py
nutrient_dws-2.0.0.dist-info/licenses/LICENSE
nutrient_dws_scripts/LLM_DOC.md
nutrient_dws_scripts/__init__.py
nutrient_dws_scripts/add_claude_code_rule.py
nutrient_dws-2.0.0.dist-info/METADATA
nutrient_dws-2.0.0.dist-info/WHEEL
nutrient_dws-2.0.0.dist-info/entry_points.txt
nutrient_dws-2.0.0.dist-info/top_level.txt
nutrient_dws-2.0.0.dist-info/RECORD
