Metadata-Version: 2.4
Name: nutrient-dws
Version: 2.0.0
Summary: Python client library for Nutrient Document Web Services API
Author-email: Nutrient <support@nutrient.io>
License-Expression: MIT
Project-URL: Homepage, https://github.com/PSPDFKit/nutrient-dws-client-python
Project-URL: Documentation, https://github.com/PSPDFKit/nutrient-dws-client-python/blob/main/README.md
Project-URL: Repository, https://github.com/PSPDFKit/nutrient-dws-client-python
Project-URL: Bug Tracker, https://github.com/PSPDFKit/nutrient-dws-client-python/issues
Keywords: nutrient,pdf,document,processing,api,client
Classifier: Development Status :: 4 - Beta
Classifier: Intended Audience :: Developers
Classifier: Operating System :: OS Independent
Classifier: Programming Language :: Python :: 3
Classifier: Programming Language :: Python :: 3.10
Classifier: Programming Language :: Python :: 3.11
Classifier: Programming Language :: Python :: 3.12
Classifier: Topic :: Software Development :: Libraries :: Python Modules
Classifier: Topic :: Office/Business
Classifier: Topic :: Multimedia :: Graphics :: Graphics Conversion
Requires-Python: >=3.10
License-File: LICENSE
Requires-Dist: httpx<1.0.0,>=0.24.0
Requires-Dist: aiofiles<25.0.0,>=23.0.0
Requires-Dist: typing_extensions>=4.9.0
Provides-Extra: dev
Requires-Dist: pytest>=7.0.0; extra == "dev"
Requires-Dist: pytest-asyncio>=0.21.0; extra == "dev"
Requires-Dist: pytest-cov>=4.0.0; extra == "dev"
Requires-Dist: mypy>=1.0.0; extra == "dev"
Requires-Dist: ruff>=0.1.0; extra == "dev"
Requires-Dist: types-aiofiles>=24.1.0; extra == "dev"
Requires-Dist: build<2,>=1.2.2.post1; extra == "dev"
Requires-Dist: twine<7,>=6.1.0; extra == "dev"
Requires-Dist: python-dotenv>=1.1.1; extra == "dev"
Dynamic: license-file
